[
  {
    "event_type": "down",
    "name": "page down",
    "time": 1680709760.492057
  },
  {
    "event_type": "up",
    "name": "page down",
    "time": 1680709760.6223497
  },
  {
    "event_type": "down",
    "name": "page down",
    "time": 1680709760.7123692
  },
  {
    "event_type": "up",
    "name": "page down",
    "time": 1680709761.2843707
  },
  {
    "event_type": "down",
    "name": "t",
    "time": 1680709761.3273797
  },
  {
    "event_type": "up",
    "name": "t",
    "time": 1680709761.5174627
  },
  {
    "event_type": "down",
    "name": "g",
    "time": 1680709762.0576637
  },
  {
    "event_type": "up",
    "name": "g",
    "time": 1680709763.3994644
  },
  {
    "event_type": "down",
    "name": "r",
    "time": 1680709763.5910118
  },
  {
    "event_type": "up",
    "name": "r",
    "time": 1680709763.6927757
  },
  {
    "event_type": "down",
    "name": "r",
    "time": 1680709763.76179
  },
  {
    "event_type": "up",
    "name": "r",
    "time": 1680709763.8988206
  },
  {
    "event_type": "down",
    "name": "page down",
    "time": 1680709764.1444836
  },
  {
    "event_type": "up",
    "name": "page down",
    "time": 1680709764.289404
  },
  {
    "event_type": "down",
    "name": "end",
    "time": 1680709764.3339205
  },
  {
    "event_type": "up",
    "name": "end",
    "time": 1680709764.4529471
  },
  {
    "event_type": "down",
    "name": "e",
    "time": 1680709764.46795
  },
  {
    "event_type": "up",
    "name": "e",
    "time": 1680709765.4390533
  },
  {
    "event_type": "down",
    "name": "q",
    "time": 1680709765.5715916
  },
  {
    "event_type": "up",
    "name": "q",
    "time": 1680709766.316854
  },
  {
    "event_type": "down",
    "name": "d",
    "time": 1680709766.480082
  },
  {
    "event_type": "up",
    "name": "d",
    "time": 1680709767.3407185
  },
  {
    "event_type": "down",
    "name": "alt",
    "time": 1680709767.6258125
  },
  {
    "event_type": "up",
    "name": "alt",
    "time": 1680709767.8218572
  },
  {
    "event_type": "down",
    "name": "3",
    "time": 1680709778.1973867
  },
  {
    "event_type": "up",
    "name": "3",
    "time": 1680709778.3234158
  },
  {
    "event_type": "down",
    "name": "x",
    "time": 1680709778.788654
  },
  {
    "event_type": "up",
    "name": "x",
    "time": 1680709778.8816721
  },

  {
    "event_type": "down",
    "name": "1",
    "time": 1680709780.7564206
  },
  {
    "event_type": "up",
    "name": "1",
    "time": 1680709780.8864496
  },
  {
    "event_type": "down",
    "name": "x",
    "time": 1680709782.2215502
  },
  {
    "event_type": "up",
    "name": "x",
    "time": 1680709782.31157
  },
    {
    "event_type": "down",
    "name": "x",
    "time": 1680709783.2215502
  },
  {
    "event_type": "up",
    "name": "x",
    "time": 1680709783.31157
  },
    {
    "event_type": "down",
    "name": "x",
    "time": 1680709784.2215502
  },
  {
    "event_type": "up",
    "name": "x",
    "time": 1680709784.31157
  },
    {
    "event_type": "down",
    "name": "x",
    "time": 1680709785.2215502
  },
  {
    "event_type": "up",
    "name": "x",
    "time": 1680709785.31157
  },
  {
    "event_type": "down",
    "name": "esc",
    "time": 1680709792.1921492
  },
  {
    "event_type": "up",
    "name": "esc",
    "time": 1680709792.2531624
  },
  {
    "event_type": "down",
    "name": "f10",
    "time": 1680709792.8050961
  },
  {
    "event_type": "up",
    "name": "f10",
    "time": 1680709792.9031184
  }
]