[
  {
    "event_type": "down",
    "name": "page down",
    "time": 1679830998.5640132
  },
  {
    "event_type": "up",
    "name": "page down",
    "time": 1679830998.6240275
  },
  {
    "event_type": "down",
    "name": "page down",
    "time": 1679830998.7070456
  },
  {
    "event_type": "down",
    "name": "page down",
    "time": 1679830999.213941
  },
  {
    "event_type": "down",
    "name": "page down",
    "time": 1679830999.2455363
  },
  {
    "event_type": "down",
    "name": "page down",
    "time": 1679830999.2765431
  },
  {
    "event_type": "down",
    "name": "page down",
    "time": 1679830999.3075504
  },
  {
    "event_type": "down",
    "name": "page down",
    "time": 1679830999.3545609
  },
  {
    "event_type": "down",
    "name": "page down",
    "time": 1679830999.385568
  },
  {
    "event_type": "up",
    "name": "page down",
    "time": 1679830999.4055722
  },
  {
    "event_type": "down",
    "name": "q",
    "time": 1679830999.4515824
  },
  {
    "event_type": "up",
    "name": "q",
    "time": 1679830999.6306226
  },
  {
    "event_type": "down",
    "name": "s",
    "time": 1679831001.0126336
  },
  {
    "event_type": "up",
    "name": "s",
    "time": 1679831001.1476657
  },
  {
    "event_type": "down",
    "name": "s",
    "time": 1679831001.6408396
  },
  {
    "event_type": "up",
    "name": "s",
    "time": 1679831001.7918754
  },
  {
    "event_type": "down",
    "name": "caps lock",
    "time": 1679831004.325301
  },
  {
    "event_type": "up",
    "name": "caps lock",
    "time": 1679831004.424324
  },
  {
    "event_type": "down",
    "name": "X",
    "time": 1679831005.2577167
  },
  {
    "event_type": "up",
    "name": "X",
    "time": 1679831005.3787446
  },
  {
    "event_type": "down",
    "name": "X",
    "time": 1679831006.0446527
  },
  {
    "event_type": "up",
    "name": "X",
    "time": 1679831006.1326873
  },
  {
    "event_type": "down",
    "name": "X",
    "time": 1679831006.774487
  },
  {
    "event_type": "up",
    "name": "X",
    "time": 1679831006.87851
  },
  {
    "event_type": "down",
    "name": "X",
    "time": 1679831007.5138702
  },
  {
    "event_type": "up",
    "name": "X",
    "time": 1679831007.626896
  },
  {
    "event_type": "down",
    "name": "X",
    "time": 1679831008.184104
  },
  {
    "event_type": "up",
    "name": "X",
    "time": 1679831008.319321
  },
  {
    "event_type": "down",
    "name": "X",
    "time": 1679831008.8679423
  },
  {
    "event_type": "up",
    "name": "X",
    "time": 1679831008.998543
  },
  {
    "event_type": "down",
    "name": "X",
    "time": 1679831009.577084
  },
  {
    "event_type": "up",
    "name": "X",
    "time": 1679831009.7181072
  },
  {
    "event_type": "down",
    "name": "end",
    "time": 1679831010.5386364
  },
  {
    "event_type": "up",
    "name": "end",
    "time": 1679831010.602651
  },
  {
    "event_type": "down",
    "name": "A",
    "time": 1679831011.3820007
  },
  {
    "event_type": "up",
    "name": "A",
    "time": 1679831011.4850237
  },
  {
    "event_type": "down",
    "name": "A",
    "time": 1679831012.0037255
  },
  {
    "event_type": "up",
    "name": "A",
    "time": 1679831012.0777423
  },
  {
    "event_type": "down",
    "name": "A",
    "time": 1679831012.5909643
  },
  {
    "event_type": "up",
    "name": "A",
    "time": 1679831012.7004929
  },
  {
    "event_type": "down",
    "name": "A",
    "time": 1679831013.2196102
  },
  {
    "event_type": "up",
    "name": "A",
    "time": 1679831013.3256338
  }
]