[
  {
    "event_type": "down",
    "name": "page down",
    "time": 1680707562.248354
  },
  {
    "event_type": "up",
    "name": "page down",
    "time": 1680707562.3123686
  },
  {
    "event_type": "down",
    "name": "page down",
    "time": 1680707562.3799746
  },
  {
    "event_type": "up",
    "name": "page down",
    "time": 1680707563.588759
  },
  {
    "event_type": "down",
    "name": "t",
    "time": 1680707563.6353245
  },
  {
    "event_type": "up",
    "name": "t",
    "time": 1680707563.774356
  },
  {
    "event_type": "down",
    "name": "f",
    "time": 1680707564.8299973
  },
  {
    "event_type": "up",
    "name": "f",
    "time": 1680707564.9490232
  },
  {
    "event_type": "down",
    "name": "end",
    "time": 1680707567.4464576
  },
  {
    "event_type": "up",
    "name": "end",
    "time": 1680707567.5174747
  },
  {
    "event_type": "down",
    "name": "a",
    "time": 1680707568.3333623
  },
  {
    "event_type": "up",
    "name": "a",
    "time": 1680707568.6981363
  },
  {
    "event_type": "down",
    "name": "a",
    "time": 1680707568.9456134
  },
  {
    "event_type": "up",
    "name": "a",
    "time": 1680707569.2771723
  },
  {
    "event_type": "down",
    "name": "a",
    "time": 1680707569.566526
  },
  {
    "event_type": "up",
    "name": "a",
    "time": 1680707569.8847077
  },
  {
    "event_type": "down",
    "name": "a",
    "time": 1680707570.176774
  },
  {
    "event_type": "up",
    "name": "a",
    "time": 1680707570.5848472
  },
  {
    "event_type": "down",
    "name": "page down",
    "time": 1680707571.0422285
  },
  {
    "event_type": "up",
    "name": "page down",
    "time": 1680707571.1172452
  },
  {
    "event_type": "down",
    "name": "page down",
    "time": 1680707571.1542532
  },
  {
    "event_type": "up",
    "name": "page down",
    "time": 1680707571.4971153
  },
  {
    "event_type": "down",
    "name": "clear",
    "time": 1680707571.5681806
  },
  {
    "event_type": "up",
    "name": "clear",
    "time": 1680707571.6790633
  },
  {
    "event_type": "down",
    "name": "end",
    "time": 1680707571.978415
  },
  {
    "event_type": "up",
    "name": "end",
    "time": 1680707572.033427
  },
  {
    "event_type": "down",
    "name": "caps lock",
    "time": 1680707573.048647
  },
  {
    "event_type": "up",
    "name": "caps lock",
    "time": 1680707573.1486695
  },
  {
    "event_type": "down",
    "name": "X",
    "time": 1680707573.6034293
  },
  {
    "event_type": "up",
    "name": "X",
    "time": 1680707573.6590295
  },
  {
    "event_type": "down",
    "name": "X",
    "time": 1680707574.2201138
  },
  {
    "event_type": "up",
    "name": "X",
    "time": 1680707574.2881289
  },
  {
    "event_type": "down",
    "name": "X",
    "time": 1680707574.8695529
  },
  {
    "event_type": "up",
    "name": "X",
    "time": 1680707574.949571
  },
  {
    "event_type": "down",
    "name": "X",
    "time": 1680707575.5987892
  },
  {
    "event_type": "up",
    "name": "X",
    "time": 1680707575.6853943
  },
  {
    "event_type": "down",
    "name": "X",
    "time": 1680707576.4177315
  },
  {
    "event_type": "up",
    "name": "X",
    "time": 1680707576.479382
  },
  {
    "event_type": "down",
    "name": "X",
    "time": 1680707577.1542082
  },
  {
    "event_type": "up",
    "name": "X",
    "time": 1680707577.2262247
  },
  {
    "event_type": "down",
    "name": "A",
    "time": 1680707596.8973637
  },
   {
    "event_type": "down",
    "name": "A",
    "time": 1680707597.0473637
  }
]